pyaides/__init__.py
pyaides/dict/__init__.py
pyaides/dict/hashable_dict.py
pyaides/files/__init__.py
pyaides/files/head.py
pyaides/files/tail.py
pyaides/logging/__init__.py
pyaides/logging/config.py
pyaides/logging/filters.py
pyaides/logging/lazy_args.py
pyaides-19.8.30.dist-info/LICENSE
pyaides-19.8.30.dist-info/METADATA
pyaides-19.8.30.dist-info/WHEEL
pyaides-19.8.30.dist-info/top_level.txt
pyaides-19.8.30.dist-info/RECORD
