Metadata-Version: 2.1
Name: pyaides
Version: 19.8.30
Summary: Light-weight Python 3 utilities
Home-page: https://github.com/okomestudio/pyaides
Author: Taro Sato
License: UNKNOWN
Platform: Linux
Requires-Python: >=3.7
Provides-Extra: test
Requires-Dist: black (==18.9b0) ; extra == 'test'
Requires-Dist: coverage (==4.5.2) ; extra == 'test'
Requires-Dist: pre-commit (==1.14.4) ; extra == 'test'
Requires-Dist: pytest (==4.2.1) ; extra == 'test'
Requires-Dist: pytest-cov (==2.6.1) ; extra == 'test'
Requires-Dist: pytest-mock (==1.10.4) ; extra == 'test'
